<?xml version="1.0" encoding="utf-8" ?>
<dwsync>
<file name="clock.swf" server="C:/Program Files/XAMPP/htdocs/variabaru/" local="128933244146250000" remote="128933244140000000" />
<file name="counter.swf" server="C:/Program Files/XAMPP/htdocs/variabaru/" local="128933244457500000" remote="128933244450000000" />
<file name="logo.swf" server="C:/Program Files/XAMPP/htdocs/variabaru/" local="128916026936718750" remote="128916026930000000" />
<file name="ContactUs.swf" server="C:/Program Files/XAMPP/htdocs/variabaru/" local="128941036190312500" remote="128941036190000000" />
<file name="clock.swf" server="C:/XAMPP/htdocs/variabaru/" local="128933244146250000" remote="128933244140000000" />
<file name="ContactUs.swf" server="C:/XAMPP/htdocs/variabaru/" local="128941036190312500" remote="128941036190000000" />
<file name="counter.swf" server="C:/XAMPP/htdocs/variabaru/" local="128933244457500000" remote="128933244450000000" />
<file name="logo.swf" server="C:/XAMPP/htdocs/variabaru/" local="128916026936718750" remote="128916026930000000" />
</dwsync>